chemaxon/_isolate_handler.py
chemaxon/molecule.py
chemaxon/__init__.py
chemaxon/_exception_util.py
chemaxon/_util.py
chemaxon/info.py
chemaxon/structurechecker/structurechecker.py
chemaxon/structurechecker/__init__.py
chemaxon/standardizer/__init__.py
chemaxon/standardizer/standardizer.py
chemaxon/io/importer.py
chemaxon/io/exporter.py
chemaxon/io/__init__.py
chemaxon/libs/chemaxon-lib_dynamic.h
chemaxon/libs/graal_isolate_dynamic.h
chemaxon/libs/chemaxon-lib.h
chemaxon/libs/chemaxon-lib.dylib
chemaxon/libs/graal_isolate.h
chemaxon/fingerprints/pfp.py
chemaxon/fingerprints/fingerprint.py
chemaxon/fingerprints/__init__.py
chemaxon/fingerprints/tanimoto.py
chemaxon/fingerprints/cfp.py
chemaxon/fingerprints/fcfp.py
chemaxon/fingerprints/ecfp.py
chemaxon/calculations/polarizability.py
chemaxon/calculations/charge.py
chemaxon/calculations/__init__.py
chemaxon/calculations/pka.py
chemaxon/calculations/logp.py
chemaxon/calculations/logp_method.py
chemaxon/calculations/hlb.py
chemaxon/calculations/major_microspecies.py
chemaxon/calculations/logd.py
chemaxon/calculations/chemterm.py
chemaxon-25.1.0b5.dist-info/RECORD
chemaxon-25.1.0b5.dist-info/WHEEL
chemaxon-25.1.0b5.dist-info/top_level.txt
chemaxon-25.1.0b5.dist-info/METADATA
chemaxon-25.1.0b5.dist-info/licenses/LICENSE.txt
