Metadata-Version: 2.4
Name: chemaxon
Version: 25.1.0b5
Summary: Chemaxon Python API
Home-page: https://chemaxon.com/
Author: Chemaxon Kft.
Author-email: chemlib@chemaxon.com
License: Chemaxon License
Keywords: chemaxon
Platform: any
Classifier: Development Status :: 4 - Beta
Classifier: Programming Language :: Python
Classifier: Topic :: Utilities
Classifier: License :: Other/Proprietary License
License-File: LICENSE.txt
Dynamic: license-file
